docuware/__init__.py
docuware/cidict.py
docuware/cijson.py
docuware/cli/__init__.py
docuware/cli/dw.py
docuware/client.py
docuware/conn.py
docuware/dialogs.py
docuware/document.py
docuware/errors.py
docuware/fields.py
docuware/filecabinet.py
docuware/organization.py
docuware/parser.py
docuware/structs.py
docuware/tasks.py
docuware/types.py
docuware/users.py
docuware/utils.py
docuware_client-0.5.3.dist-info/METADATA
docuware_client-0.5.3.dist-info/WHEEL
docuware_client-0.5.3.dist-info/entry_points.txt
docuware_client-0.5.3.dist-info/licenses/LICENSE
docuware_client-0.5.3.dist-info/RECORD
