Metadata-Version: 2.4
Name: docuware-client
Version: 0.5.3
Summary: DocuWare REST-API client
License: BSD-3-Clause
License-File: LICENSE
Author: Stefan Schönberger
Author-email: mail@sniner.dev
Requires-Python: >=3.9
Classifier: License :: OSI Approved :: BSD License
Classifier: Operating System :: OS Independent
Classifier: Programming Language :: Python :: 3
Classifier: Programming Language :: Python :: 3.9
Classifier: Programming Language :: Python :: 3.10
Classifier: Programming Language :: Python :: 3.11
Classifier: Programming Language :: Python :: 3.12
Classifier: Programming Language :: Python :: 3.13
Classifier: Programming Language :: Python :: 3.14
Requires-Dist: requests (>=2.32.3,<3.0.0)
Project-URL: Repository, https://github.com/sniner/docuware-client
